README.md
setup.py
robertoltlibpythonpro/__init__.py
robertoltlibpythonpro/github_api.py
robertoltlibpythonpro.egg-info/PKG-INFO
robertoltlibpythonpro.egg-info/SOURCES.txt
robertoltlibpythonpro.egg-info/dependency_links.txt
robertoltlibpythonpro.egg-info/not-zip-safe
robertoltlibpythonpro.egg-info/requires.txt
robertoltlibpythonpro.egg-info/top_level.txt