Metadata-Version: 2.1
Name: robertoltlibpythonpro
Version: 0.2
Summary: Module to exemplify the creations of releases
Home-page: https://github.com/robertolt/robertollibpythonpro
Author: Robertolt
Author-email: rl.beto.lorenzoni@gmail.com
License: GNU AFFERO GENERAL PUBLIC LICENSE
Platform: UNKNOWN
Classifier: Development Status :: 2 - Pre-Alpha
Classifier: Environment :: Console
Classifier: Intended Audience :: Developers
Classifier: License :: OSI Approved :: GNU Affero General Public License v3 or later (AGPLv3+)
Classifier: Operating System :: OS Independent
Classifier: Programming Language :: Python
Classifier: Programming Language :: Python :: 3.6
Classifier: Framework :: Pytest
